tuicord/__init__.py
tuicord/components/__init__.py
tuicord/components/channel_message.py
tuicord/components/channels_tree.py
tuicord/components/input_box.py
tuicord/components/server_button.py
tuicord/core/__init__.py
tuicord/core/discord_client.py
tuicord/core/styles/style.css
tuicord/core/tui_interface.py
tuicord/main.py
tuicord/utils.py
tuicord-0.1.0.dist-info/entry_points.txt
tuicord-0.1.0.dist-info/LICENSE
tuicord-0.1.0.dist-info/METADATA
tuicord-0.1.0.dist-info/WHEEL
tuicord-0.1.0.dist-info/RECORD
