Metadata-Version: 2.1
Name: tuicord
Version: 0.1.0
Summary: 
Author: Robert Nogueira
Author-email: robertlucasnogueira@gmail.com
Requires-Python: >=3.9,<4.0
Classifier: Programming Language :: Python :: 3
Classifier: Programming Language :: Python :: 3.9
Classifier: Programming Language :: Python :: 3.10
Classifier: Programming Language :: Python :: 3.11
Requires-Dist: click (>=8.1.6,<9.0.0)
Requires-Dist: discord-py-self (>=2.0.0,<3.0.0)
Requires-Dist: python-dotenv (>=1.0.0,<2.0.0)
Requires-Dist: textual (>=0.29.0,<0.30.0)
Requires-Dist: textual-dev (>=1.0.1,<2.0.0)
